karrio/server/graph/__init__.py
karrio/server/graph/admin.py
karrio/server/graph/apps.py
karrio/server/graph/forms.py
karrio/server/graph/models.py
karrio/server/graph/schema.py
karrio/server/graph/serializers.py
karrio/server/graph/urls.py
karrio/server/graph/utils.py
karrio/server/graph/views.py
karrio/server/graph/management/__init__.py
karrio/server/graph/management/commands/__init__.py
karrio/server/graph/management/commands/export_schema.py
karrio/server/graph/migrations/0001_initial.py
karrio/server/graph/migrations/0002_auto_20210512_1353.py
karrio/server/graph/migrations/0003_remove_template_customs.py
karrio/server/graph/migrations/__init__.py
karrio/server/graph/schemas/__init__.py
karrio/server/graph/schemas/base/__init__.py
karrio/server/graph/schemas/base/inputs.py
karrio/server/graph/schemas/base/mutations.py
karrio/server/graph/schemas/base/types.py
karrio/server/graph/templates/graphql/graphiql.html
karrio/server/graph/templates/karrio/email_change_email.html
karrio/server/graph/templates/karrio/email_change_email.txt
karrio/server/graph/templates/karrio/password_reset_email.html
karrio/server/graph/tests/__init__.py
karrio/server/graph/tests/base.py
karrio/server/graph/tests/test_carrier_connections.py
karrio/server/graph/tests/test_metafield.py
karrio/server/graph/tests/test_partial_shipments.py
karrio/server/graph/tests/test_pickups.py
karrio/server/graph/tests/test_rate_sheets.py
karrio/server/graph/tests/test_registration.py
karrio/server/graph/tests/test_templates.py
karrio/server/graph/tests/test_user_info.py
karrio/server/settings/graph.py
karrio_server_graph-2026.1.4.dist-info/METADATA
karrio_server_graph-2026.1.4.dist-info/WHEEL
karrio_server_graph-2026.1.4.dist-info/top_level.txt
karrio_server_graph-2026.1.4.dist-info/RECORD
